geojsonpy/__init__.py
geojsonpy/geojsonpy.py
geojsonpy-0.0.2.dist-info/LICENSE
geojsonpy-0.0.2.dist-info/METADATA
geojsonpy-0.0.2.dist-info/WHEEL
geojsonpy-0.0.2.dist-info/entry_points.txt
geojsonpy-0.0.2.dist-info/top_level.txt
geojsonpy-0.0.2.dist-info/RECORD
