Metadata-Version: 2.1
Name: geojsonpy
Version: 0.0.2
Summary: Open GeoJSON data on geojson.io from Python
Home-page: https://github.com/pietrolechthaler/geojsonpy
Author: Pietro Lechthaler
Author-email: pietrolechthaler@gmail.com
License: BSD
Classifier: Intended Audience :: Developers
Classifier: Natural Language :: English
Classifier: License :: OSI Approved :: BSD License
Classifier: Programming Language :: Python :: 2.7
Requires-Python: >=3.7
License-File: LICENSE
Requires-Dist: github3.py
Requires-Dist: six
Provides-Extra: test
Requires-Dist: pytest ; extra == 'test'
Requires-Dist: mock ; extra == 'test'
